{
  "film": {
    "title": "Harry Potter and the Order of the Phoenix",
    "overview": "Returning for his fifth year of study at Hogwarts, Harry is stunned to find that his warnings about the return of Lord Voldemort have been ignored. Left with no choice, Harry takes matters into his own hands, training a small group of students – dubbed 'Dumbledore's Army' – to defend themselves against the dark arts.",
    "imageUrl": "https://image.tmdb.org/t/p/w600_and_h900_bestv2/4YnLxYLHhT4UQ8i9jxAXWy46Xuw.jpg",
    "imdbScore": "7.6",
    "trailerLink": "https://www.youtube.com/watch?v=WIj9DYJ5EKk"
  }
}